{
    "name": "Corporate",
    "slug": "corporate",
    "version": "1.0.0",
    "description": "Professional business theme for Karma CMS",
    "author": "Karma Team",
    "screenshot": "screenshot.png",
    "features": ["dark_mode", "mega_menu", "adsense"],
    "widget_areas": [
        {"id": "header", "name": "Header Navigation"},
        {"id": "sidebar", "name": "Main Sidebar"},
        {"id": "footer-1", "name": "Footer Column 1"},
        {"id": "footer-2", "name": "Footer Column 2"},
        {"id": "footer-3", "name": "Footer Column 3"}
    ]
}
